steady_queue/__init__.py
steady_queue/admin.py
steady_queue/app_executor.py
steady_queue/apps.py
steady_queue/arguments.py
steady_queue/backend.py
steady_queue/collections.py
steady_queue/concurrency.py
steady_queue/configuration.py
steady_queue/db_router.py
steady_queue/queue_selector.py
steady_queue/recurring_schedule.py
steady_queue/recurring_task.py
steady_queue/task.py
steady_queue/management/__init__.py
steady_queue/management/commands/__init__.py
steady_queue/management/commands/steady_queue.py
steady_queue/migrations/0001_initial.py
steady_queue/migrations/__init__.py
steady_queue/models/__init__.py
steady_queue/models/base.py
steady_queue/models/blocked_execution.py
steady_queue/models/claimed_execution.py
steady_queue/models/clearable.py
steady_queue/models/concurrency_controls.py
steady_queue/models/dispatching.py
steady_queue/models/executable.py
steady_queue/models/execution.py
steady_queue/models/executor.py
steady_queue/models/failed_execution.py
steady_queue/models/job.py
steady_queue/models/pause.py
steady_queue/models/process.py
steady_queue/models/prunable.py
steady_queue/models/queue.py
steady_queue/models/ready_execution.py
steady_queue/models/recurring_execution.py
steady_queue/models/recurring_task.py
steady_queue/models/retryable.py
steady_queue/models/schedulable.py
steady_queue/models/scheduled_execution.py
steady_queue/models/semaphore.py
steady_queue/processes/__init__.py
steady_queue/processes/base.py
steady_queue/processes/concurrent.py
steady_queue/processes/dispatcher.py
steady_queue/processes/errors.py
steady_queue/processes/interruptible.py
steady_queue/processes/maintenance.py
steady_queue/processes/pidfile.py
steady_queue/processes/pidfiled.py
steady_queue/processes/poller.py
steady_queue/processes/pool.py
steady_queue/processes/registrable.py
steady_queue/processes/runnable.py
steady_queue/processes/scheduler.py
steady_queue/processes/signals.py
steady_queue/processes/supervised.py
steady_queue/processes/supervisor.py
steady_queue-0.1.2.dist-info/licenses/LICENSE
steady_queue-0.1.2.dist-info/METADATA
steady_queue-0.1.2.dist-info/WHEEL
steady_queue-0.1.2.dist-info/top_level.txt
steady_queue-0.1.2.dist-info/RECORD
