Metadata-Version: 2.4
Name: steady-queue
Version: 0.1.2
Summary: An asynchronous task library for Django that supports delayed tasks, concurrency controls, recurring tasks, pausing queues, numeric priorities per task, priorities by queue order and bulk enqueueing.
Author-email: Elias Hernandis <elias@hernandis.me>
License-Expression: MIT
Project-URL: Homepage, https://github.com/knifecake/steady-queue
Project-URL: Source, https://github.com/knifecake/steady-queue
Project-URL: Documentation, https://steady-queue.readthedocs.io/en/latest/
Project-URL: Tracker, https://github.com/knifecake/steady-queue/issues
Project-URL: Releases, https://github.com/knifecake/steady-queue/releases
Keywords: django,tasks,async,jobs,queues
Classifier: Framework :: Django
Classifier: Framework :: Django :: 6.0
Classifier: Programming Language :: Python :: 3.12
Classifier: Programming Language :: Python :: 3.13
Classifier: Operating System :: OS Independent
Classifier: Natural Language :: English
Requires-Python: >=3.12
License-File: LICENSE
Requires-Dist: crontab>=1.0.5
Requires-Dist: django<7,>=6.0
Dynamic: license-file
